apispec_aiohttp/__init__.py
apispec_aiohttp/constants.py
apispec_aiohttp/core.py
apispec_aiohttp/middlewares.py
apispec_aiohttp/py.typed
apispec_aiohttp/route_processor.py
apispec_aiohttp/spec.py
apispec_aiohttp/swagger_ui.py
apispec_aiohttp/typedefs.py
apispec_aiohttp/utils.py
apispec_aiohttp/validation.py
apispec_aiohttp/decorators/__init__.py
apispec_aiohttp/decorators/docs.py
apispec_aiohttp/decorators/request.py
apispec_aiohttp/decorators/response.py
apispec_aiohttp/swagger_ui/VERSION
apispec_aiohttp/swagger_ui/favicon-16x16.png
apispec_aiohttp/swagger_ui/favicon-32x32.png
apispec_aiohttp/swagger_ui/index.css
apispec_aiohttp/swagger_ui/index.html
apispec_aiohttp/swagger_ui/oauth2-redirect.html
apispec_aiohttp/swagger_ui/swagger-initializer.js
apispec_aiohttp/swagger_ui/swagger-ui-bundle.js
apispec_aiohttp/swagger_ui/swagger-ui-bundle.js.map
apispec_aiohttp/swagger_ui/swagger-ui-es-bundle-core.js
apispec_aiohttp/swagger_ui/swagger-ui-es-bundle-core.js.map
apispec_aiohttp/swagger_ui/swagger-ui-es-bundle.js
apispec_aiohttp/swagger_ui/swagger-ui-es-bundle.js.map
apispec_aiohttp/swagger_ui/swagger-ui-standalone-preset.js
apispec_aiohttp/swagger_ui/swagger-ui-standalone-preset.js.map
apispec_aiohttp/swagger_ui/swagger-ui.css
apispec_aiohttp/swagger_ui/swagger-ui.css.map
apispec_aiohttp/swagger_ui/swagger-ui.js
apispec_aiohttp/swagger_ui/swagger-ui.js.map
apispec_aiohttp-0.4.3.dist-info/METADATA
apispec_aiohttp-0.4.3.dist-info/WHEEL
apispec_aiohttp-0.4.3.dist-info/licenses/LICENSE
apispec_aiohttp-0.4.3.dist-info/RECORD
