Metadata-Version: 2.4
Name: apispec-aiohttp
Version: 0.4.3
Summary: API documentation and validation for aiohttp using apispec
Project-URL: Homepage, https://github.com/kulapard/apispec-aiohttp
Project-URL: Issues, https://github.com/kulapard/apispec-aiohttp/issues
Author-email: Taras Drapalyuk <taras@drapalyuk.com>
License: Apache-2.0
License-File: LICENSE
Keywords: aiohttp,apispec,marshmallow,swagger
Classifier: Development Status :: 5 - Production/Stable
Classifier: Intended Audience :: Developers
Classifier: License :: OSI Approved :: Apache Software License
Classifier: Natural Language :: English
Classifier: Programming Language :: Python :: 3.10
Classifier: Programming Language :: Python :: 3.11
Classifier: Programming Language :: Python :: 3.12
Classifier: Programming Language :: Python :: 3.13
Requires-Python: >=3.10
Requires-Dist: aiohttp<4.0.0,>=3.10.0
Requires-Dist: apispec<7.0.0,>=5.0.1
Requires-Dist: marshmallow<4.0.0,>=3.0.1
Requires-Dist: webargs<9.0.0,>=8.0.1
